{
  "name": "Blindness/Deafness",
  "type": "spell",
  "flags": {
    "core": {
      "sourceId": "Item.9YZVeks3FER7Whud"
    },
    "exportSource": {
      "world": "testorld",
      "system": "D35E",
      "coreVersion": "0.7.9",
      "systemVersion": "0.88.2"
    }
  },
  "img": "systems/D35E/icons/spells/named-spells/blindness-deafness.png",
  "effects": [],
  "_id": "1DX3mgs4fxZVvTNg",
  "system": {
    "originVersion": 99,
    "originPack": "",
    "originId": "",
    "possibleUpdate": false,
    "description": {
      "value": "<div class=\"spell-description\">\n  <p>\n      <strong>School:</strong>&nbsp;necromancy;\n    <br>\n    \n    <strong>Domain:</strong>&nbsp;Darkness 2;\n    \n    \n    \n    <br>\n    <strong>Components:</strong>&nbsp;V<br>\n    \n      <strong>Casting Time:</strong>&nbsp;1 standard action<br>\n    <strong>Range:</strong>&nbsp;medium (100 ft. + 10 ft./level)<br>\n    \n    <strong>Target:</strong>&nbsp;one living creature<br>\n    \n    <strong>Duration:</strong>&nbsp;Permanent (D)<br>\n    \n        <strong>Saving Throw:</strong>&nbsp;Fortitude negates\n        <br>\n        <strong>Spell Resistance:</strong>&nbsp;yes<br>\n  </p>\n  <h2>Description</h2>\n  \n\n\n<p>\nYou call upon the powers of unlife to render the subject blinded or deafened, as you choose.\n</p>\n<hr/>\n\n\n\n</div>\n",
      "chat": "",
      "unidentified": ""
    },
    "epic": "",
    "psionic": "",
    "nameFormula": "",
    "nameFromFormula": false,
    "tags": [],
    "uniqueId": "racial-blinddeaf",
    "linkId": "",
    "linkSourceId": "",
    "linkImported": false,
    "linkSourceName": "",
    "source": "",
    "classSource": "",
    "userNonRemovable": false,
    "customAttributes": {},
    "customAttributesLocked": false,
    "customTag": "",
    "createdBy": "",
    "activation": {
      "cost": 1,
      "type": "standard"
    },
    "duration": {
      "value": null,
      "units": ""
    },
    "target": {
      "value": "one living creature"
    },
    "range": {
      "value": null,
      "units": "medium",
      "long": null
    },
    "recharge": {
      "enabled": false,
      "formula": "",
      "current": 0,
      "value": null,
      "charged": false,
      "_deprecated": true
    },
    "uses": {
      "value": 0,
      "max": 0,
      "per": "",
      "autoDeductCharges": true,
      "allowMultipleUses": false,
      "chargesPerUse": 1,
      "maxPerUse": null,
      "maxPerUseFormula": "",
      "maxFormula": "",
      "rechargeFormula": null,
      "isResource": false,
      "canBeLinked": false
    },
    "requiresPsionicFocus": false,
    "linkedChargeItem": {
      "id": null,
      "img": null,
      "name": null
    },
    "measureTemplate": {
      "type": "",
      "size": 0,
      "overrideColor": false,
      "customColor": "",
      "overrideTexture": false,
      "customTexture": ""
    },
    "actionType": "other",
    "attackBonus": "",
    "critConfirmBonus": "",
    "damage": {
      "parts": [],
      "alternativeParts": []
    },
    "summon": [],
    "attackParts": [],
    "autoscaleAttackParts": "",
    "formula": "",
    "attackCountFormula": "",
    "maxDamageDice": 0,
    "maxDamageDiceFormula": "",
    "ability": {
      "attack": "",
      "damage": "",
      "damageMult": 1,
      "critRange": 20,
      "critMult": 2,
      "twoHandedOnly": false,
      "vsTouchAc": false
    },
    "save": {
      "dc": "0",
      "description": "Fortitude negates",
      "ability": "",
      "type": "",
      "dcAutoType": "",
      "dcAutoAbility": "",
      "originVersion": 97
    },
    "baseCl": "0",
    "sr": true,
    "pr": false,
    "metamagicFeats": {
      "maximized": false,
      "empowered": false,
      "enlarged": false,
      "intensified": false,
      "enhanced": false,
      "enhancedHalf": false,
      "widened": false
    },
    "effectNotes": "",
    "attackNotes": "",
    "specialActions": [],
    "favorite": false,
    "rollTableDraw": {
      "formula": "",
      "name": "",
      "pack": "",
      "id": ""
    },
    "learnedAt": {
      "class": [],
      "domain": [
        [
          "Darkness",
          2
        ]
      ],
      "subDomain": [],
      "elementalSchool": [],
      "bloodline": []
    },
    "level": 2,
    "clOffset": 0,
    "slOffset": 0,
    "school": "nec",
    "subschool": "",
    "types": "",
    "components": {
      "value": "",
      "verbal": true,
      "somatic": false,
      "material": false,
      "focus": false,
      "divineFocus": 0
    },
    "castTime": "",
    "conditionals": [],
    "materials": {
      "value": "",
      "consumed": {
        "value": false,
        "_deprecated": true
      },
      "focus": ""
    },
    "isSpellSpontaneousReplacement": false,
    "spellbook": "primary",
    "preparation": {
      "preparedAmount": 1,
      "maxAmount": 1,
      "autoDeductCharges": true,
      "mode": "prepared"
    },
    "atWill": false,
    "powerPointsCost": 0,
    "display": "",
    "isPower": false,
    "shortDescription": "\n\n\n<p>\nYou call upon the powers of unlife to render the subject blinded or deafened, as you choose.\n</p>\n<hr/>\n\n\n",
    "snip": "Makes subject blind or deaf.",
    "spellDuration": "Permanent (D)",
    "spellEffect": "",
    "spellArea": "",
    "spellType": {
      "value": "",
      "_deprecated": true
    },
    "showInQuickbar": false,
    "specialPrepared": false,
    "isDomainSpell": false,
    "specialId": null,
    "changeFlags": {
      "loseDexToAC": false,
      "noStr": false,
      "noDex": false,
      "noInt": false,
      "noCon": false,
      "oneInt": false,
      "oneWis": false,
      "oneCha": false,
      "noEncumbrance": false,
      "mediumArmorFullSpeed": false,
      "heavyArmorFullSpeed": false,
      "multiAttack": false,
      "multiweaponAttack": false,
      "uncannyDodge": false
    },
    "conditionFlags": {
      "dazzled": false,
      "wildshaped": false,
      "polymorphed": false
    },
    "associations": {
      "classes": []
    },
    "spellSpecialization": {
      "isDomain": false,
      "spells": {
        "level1": {
          "level": 1,
          "name": "",
          "img": "",
          "pack": null,
          "id": null
        },
        "level2": {
          "level": 2,
          "name": "",
          "img": "",
          "pack": null,
          "id": null
        },
        "level3": {
          "level": 3,
          "name": "",
          "img": "",
          "pack": null,
          "id": null
        },
        "level4": {
          "level": 4,
          "name": "",
          "img": "",
          "pack": null,
          "id": null
        },
        "level5": {
          "level": 5,
          "name": "",
          "img": "",
          "pack": null,
          "id": null
        },
        "level6": {
          "level": 6,
          "name": "",
          "img": "",
          "pack": null,
          "id": null
        },
        "level7": {
          "level": 7,
          "name": "",
          "img": "",
          "pack": null,
          "id": null
        },
        "level8": {
          "level": 8,
          "name": "",
          "img": "",
          "pack": null,
          "id": null
        },
        "level9": {
          "level": 9,
          "name": "",
          "img": "",
          "pack": null,
          "id": null
        }
      }
    },
    "links": {
      "charges": []
    },
    "attack": {
      "parts": []
    },
    "index": {
      "subType": null,
      "uniqueId": "racial-blinddeaf"
    }
  },
  "ownership": {
    "default": 0,
    "gvVvJrAyZKOZnAuP": 3
  },
  "folder": null,
  "sort": 0,
  "_stats": {
    "systemId": "D35E",
    "systemVersion": "2.1.3",
    "coreVersion": "10.291",
    "createdTime": null,
    "modifiedTime": 1678394275409,
    "lastModifiedBy": "cB3ob9BYxSFYX7sd"
  },
  "_key": "!items!1DX3mgs4fxZVvTNg"
}