{
  "_id": "BO4qIhRoZvQaUldo",
  "name": "Shield of Faith",
  "type": "spell",
  "sort": 600000,
  "flags": {},
  "img": "systems/D35E/icons/spells/named-spells/shield-of-faith.png",
  "effects": [],
  "folder": null,
  "system": {
    "originVersion": 0,
    "originPack": "",
    "originId": "",
    "possibleUpdate": false,
    "description": {
      "value": "<div class=\"spell-description\">\n  <p>\n      <strong>School:</strong>&nbsp;abjuration;\n    <br>\n    <strong>Level:</strong>&nbsp;Cleric 1;\n    \n    \n    \n    \n    <br>\n    <strong>Components:</strong>&nbsp;V, S, M (a small parchment with a bit of holy text written upon it)<br>\n    \n      <strong>Casting Time:</strong>&nbsp;1 standard action<br>\n    <strong>Range:</strong>&nbsp;touch<br>\n    \n    <strong>Target:</strong>&nbsp;creature touched\n<br>\n    \n    <strong>Duration:</strong>&nbsp;1 min./level\n<br>\n    \n        <strong>Saving Throw:</strong>&nbsp;Will negates (harmless)\n\n        <br>\n        <strong>Spell Resistance:</strong>&nbsp;yes<br>\n  </p>\n  <h2>Description</h2>\n  \n\n\n<p>\nThis spell creates a shimmering, magical field around the touched creature that averts attacks. The spell grants the subject a +2 deflection bonus to AC, with an additional +1 to the bonus for every six levels you have (maximum +5 deflection bonus at 18th level).\n</p><p><i>Material Component: </i>A small parchment with a bit of holy text written upon it.\n</p>\n<hr/>\n\n\n\n</div>\n",
      "chat": "",
      "unidentified": ""
    },
    "epic": "",
    "psionic": "",
    "nameFormula": "",
    "nameFromFormula": false,
    "tags": [],
    "uniqueId": "",
    "addedLevel": 0,
    "linkId": "",
    "linkSourceId": "",
    "linkImported": false,
    "linkSourceName": "",
    "source": "",
    "classSource": "",
    "userNonRemovable": false,
    "customAttributes": {},
    "customAttributesLocked": false,
    "customTag": "",
    "createdBy": "",
    "activation": {
      "cost": 1,
      "type": "standard"
    },
    "duration": {
      "value": null,
      "units": ""
    },
    "target": {
      "value": "creature touched\n"
    },
    "range": {
      "value": null,
      "units": "touch",
      "long": null
    },
    "recharge": {
      "enabled": false,
      "formula": "",
      "current": 0
    },
    "uses": {
      "value": 0,
      "max": 0,
      "per": "",
      "autoDeductCharges": true,
      "allowMultipleUses": false,
      "chargesPerUse": 1,
      "maxPerUse": null,
      "maxPerUseFormula": "",
      "maxFormula": "",
      "rechargeFormula": null,
      "isResource": false,
      "canBeLinked": false
    },
    "requiresPsionicFocus": false,
    "linkedChargeItem": {
      "id": null,
      "img": null,
      "name": null
    },
    "measureTemplate": {
      "type": "",
      "size": 0,
      "overrideColor": false,
      "customColor": "",
      "overrideTexture": false,
      "customTexture": ""
    },
    "actionType": "other",
    "attackBonus": "",
    "critConfirmBonus": "",
    "damage": {
      "parts": [],
      "alternativeParts": []
    },
    "summon": [],
    "attackParts": [],
    "autoscaleAttackParts": "",
    "formula": "",
    "attackCountFormula": "",
    "maxDamageDice": 0,
    "maxDamageDiceFormula": "",
    "ability": {
      "attack": "",
      "damage": "",
      "damageMult": 1,
      "critRange": 20,
      "critMult": 2,
      "twoHandedOnly": false,
      "vsTouchAc": false
    },
    "save": {
      "dc": "0",
      "description": "Will negates (harmless)\n",
      "ability": "",
      "type": "",
      "dcAutoType": "",
      "dcAutoAbility": ""
    },
    "baseCl": "0",
    "sr": true,
    "pr": false,
    "metamagicFeats": {
      "maximized": false,
      "empowered": false,
      "enlarged": false,
      "intensified": false,
      "enhanced": false,
      "enhancedHalf": false,
      "widened": false
    },
    "effectNotes": "",
    "attackNotes": "",
    "specialActions": [],
    "favorite": false,
    "rollTableDraw": {
      "formula": "",
      "name": "",
      "pack": "",
      "id": ""
    },
    "learnedAt": {
      "class": [
        [
          "Cleric",
          1
        ]
      ],
      "domain": [],
      "subDomain": [],
      "elementalSchool": [],
      "bloodline": []
    },
    "level": 1,
    "clOffset": 0,
    "slOffset": 0,
    "school": "abj",
    "subschool": "",
    "types": "",
    "components": {
      "value": "",
      "verbal": true,
      "somatic": true,
      "material": true,
      "focus": false,
      "divineFocus": 0
    },
    "castTime": "",
    "conditionals": [],
    "materials": {
      "value": "a small parchment with a bit of holy text written upon it",
      "consumed": {
        "value": false,
        "_deprecated": true
      },
      "focus": ""
    },
    "isSpellSpontaneousReplacement": false,
    "spellbook": "primary",
    "preparation": {
      "preparedAmount": 0,
      "maxAmount": 0,
      "autoDeductCharges": true,
      "mode": "prepared"
    },
    "atWill": false,
    "powerPointsCost": 0,
    "display": "",
    "isPower": false,
    "shortDescription": "\n\n\n<p>\nThis spell creates a shimmering, magical field around the touched creature that averts attacks. The spell grants the subject a +2 deflection bonus to AC, with an additional +1 to the bonus for every six levels you have (maximum +5 deflection bonus at 18th level).\n</p><p><i>Material Component: </i>A small parchment with a bit of holy text written upon it.\n</p>\n<hr/>\n\n\n",
    "snip": "Aura grants +2 or higher deflection bonus.",
    "spellDuration": "1 min./level\n",
    "spellEffect": "",
    "spellArea": "",
    "spellType": {
      "value": "",
      "_deprecated": true
    },
    "showInQuickbar": false,
    "specialPrepared": false,
    "isDomainSpell": false,
    "specialId": null,
    "customReferenceId": "",
    "attack": {
      "parts": []
    },
    "index": {
      "subType": null,
      "uniqueId": ""
    }
  },
  "ownership": {
    "default": 0
  },
  "_stats": {
    "systemId": "D35E",
    "systemVersion": "2.3.2",
    "coreVersion": "11.311",
    "createdTime": null,
    "modifiedTime": 1699168042557,
    "lastModifiedBy": "qG24w3IqZQgON3kE"
  },
  "_key": "!actors.items!rtZLpvXoHJJ3Xe88.BO4qIhRoZvQaUldo"
}