{
  "_id": "GvT7kiKZsmvnNz7i",
  "name": "Sunburst",
  "type": "spell",
  "img": "systems/D35E/icons/spells/named-spells/sunburst.png",
  "effects": [],
  "folder": null,
  "sort": 600000,
  "flags": {
    "core": {
      "sourceId": "Item.sJ0a9Lp8xcnM8bs2"
    }
  },
  "system": {
    "originVersion": 109,
    "originPack": "D35E.spells",
    "originId": "GvT7kiKZsmvnNz7i",
    "possibleUpdate": false,
    "description": {
      "value": "<div class=\"spell-description\">\n  <p>\n      <strong>School:</strong>&nbsp;evocation&nbsp;[light];\n    <br>\n    <strong>Level:</strong>&nbsp;Druid 8, Sorcerer 8, Wizard 8;\n    <strong>Domain:</strong>&nbsp;Sun 8;\n    \n    \n    \n    <br>\n    <strong>Components:</strong>&nbsp;V, S, M/DF (a piece of sunstone and a naked flame), F<br>\n    \n      <strong>Casting Time:</strong>&nbsp;1 standard action<br>\n    <strong>Range:</strong>&nbsp;long (400 ft. + 40 ft./level)<br>\n    <strong>Area:</strong>&nbsp;80-ft.-radius burst<br>\n    \n    \n    <strong>Duration:</strong>&nbsp;Instantaneous<br>\n    <strong>Power Points/Spell Points Cost:</strong>&nbsp;15<br>\n        <strong>Saving Throw:</strong>&nbsp;Reflex Half\n        <br>\n        <strong>Spell Resistance:</strong>&nbsp;yes<br>\n  </p>\n  <h2>Description</h2>\n  \n\n\n<p>\n<i>Sunburst </i>causes a globe of searing radiance to explode silently from a point you select. All creatures in the globe are blinded and take 6d6 points of damage. A creature to which sunlight is harmful or unnatural takes double damage. A successful Reflex save negates the blindness and reduces the damage by half.\n</p><p>An undead creature caught within the globe takes 1d6 points of damage per caster level (maximum 25d6), or half damage if a Reflex save is successful. In addition, the burst results in the destruction of any undead creature specifically harmed by bright light if it fail its save.\n</p><p>The ultraviolet light generated by the spell deals damage to fungi, mold, oozes, and slimes just as if they were undead creatures.\n</p><p><i>Sunburst </i>dispels any darkness spells of lower than 9th level within its area.\n</p><p><i>Arcane Material Component: </i>A piece of sunstone and a naked flame.\n</p>\n<hr/>\n\n\n\n</div>\n",
      "chat": "",
      "unidentified": ""
    },
    "epic": "",
    "psionic": "",
    "nameFormula": "",
    "nameFromFormula": false,
    "tags": [],
    "uniqueId": "",
    "linkId": "",
    "linkSourceId": "",
    "linkImported": false,
    "linkSourceName": "",
    "source": "",
    "classSource": "",
    "userNonRemovable": false,
    "customAttributes": {},
    "customAttributesLocked": false,
    "customTag": "",
    "createdBy": "",
    "activation": {
      "cost": 1,
      "type": "standard"
    },
    "duration": {
      "value": null,
      "units": ""
    },
    "target": {
      "value": ""
    },
    "range": {
      "value": null,
      "units": "long",
      "long": null
    },
    "recharge": {
      "enabled": false,
      "formula": "",
      "current": 0
    },
    "uses": {
      "value": 0,
      "max": 0,
      "per": "",
      "autoDeductCharges": true,
      "allowMultipleUses": false,
      "chargesPerUse": 1,
      "maxPerUse": null,
      "maxPerUseFormula": "",
      "maxFormula": "",
      "rechargeFormula": null,
      "isResource": false,
      "canBeLinked": false
    },
    "requiresPsionicFocus": false,
    "linkedChargeItem": {
      "id": null,
      "img": null,
      "name": null
    },
    "measureTemplate": {
      "type": "circle",
      "size": "80",
      "overrideColor": false,
      "customColor": "",
      "overrideTexture": false,
      "customTexture": ""
    },
    "actionType": "spellsave",
    "attackBonus": "",
    "critConfirmBonus": "",
    "damage": {
      "parts": [
        [
          "6d6",
          null,
          "damage-untyped-energy"
        ]
      ],
      "alternativeParts": []
    },
    "summon": [],
    "attackParts": [],
    "autoscaleAttackParts": "",
    "formula": "",
    "attackCountFormula": "",
    "maxDamageDice": 0,
    "maxDamageDiceFormula": "",
    "ability": {
      "attack": "",
      "damage": "",
      "damageMult": 1,
      "critRange": 20,
      "critMult": 2,
      "twoHandedOnly": false,
      "vsTouchAc": false
    },
    "save": {
      "dc": "0",
      "description": "Reflex partial; see text",
      "ability": "",
      "type": "reflexhalf",
      "dcAutoType": "",
      "dcAutoAbility": "",
      "originVersion": 97
    },
    "baseCl": "0",
    "sr": true,
    "pr": false,
    "metamagicFeats": {
      "maximized": false,
      "empowered": false,
      "enlarged": false,
      "intensified": false,
      "enhanced": false,
      "enhancedHalf": false,
      "widened": false
    },
    "effectNotes": "Targets are blinded (Reflex negates)\nAny creatures to which sunlight is harmful or unnatural take double damage  (Reflex half)\nUndead targets specifically harmed by bright light are destroyed (Reflex negates)\nSunburst dispels any darkness spells of lower than 9th level within its area",
    "attackNotes": "Use alternative damage [[min(25,max(1,(@cl)))d6]] for undead, fungi, mold, oozes and slime creatures (Reflex half)",
    "specialActions": [
      {
        "name": "Blinded",
        "action": "Condition set blind to true on target",
        "condition": "",
        "img": "systems/D35E/icons/conditions/blind.png"
      }
    ],
    "favorite": false,
    "rollTableDraw": {
      "formula": "",
      "name": "",
      "pack": "",
      "id": ""
    },
    "learnedAt": {
      "class": [
        [
          "Druid",
          8
        ],
        [
          "Wizard",
          8
        ],
        [
          "Sorcerer",
          8
        ]
      ],
      "domain": [
        [
          "Sun",
          8
        ]
      ],
      "subDomain": [],
      "elementalSchool": [],
      "bloodline": []
    },
    "level": 8,
    "clOffset": 0,
    "slOffset": 0,
    "school": "evo",
    "subschool": "",
    "types": "light",
    "components": {
      "value": "",
      "verbal": true,
      "somatic": true,
      "material": true,
      "focus": true,
      "divineFocus": 2
    },
    "castTime": "",
    "conditionals": [],
    "materials": {
      "value": "a piece of sunstone and a naked flame",
      "consumed": {
        "value": false,
        "_deprecated": true
      },
      "focus": ""
    },
    "isSpellSpontaneousReplacement": false,
    "spellbook": "primary",
    "preparation": {
      "preparedAmount": 0,
      "maxAmount": 0,
      "autoDeductCharges": true,
      "mode": "prepared"
    },
    "atWill": false,
    "powerPointsCost": 15,
    "display": "",
    "isPower": false,
    "shortDescription": "\n\n\n<p>\n<i>Sunburst </i>causes a globe of searing radiance to explode silently from a point you select. All creatures in the globe are blinded and take 6d6 points of damage. A creature to which sunlight is harmful or unnatural takes double damage. A successful Reflex save negates the blindness and reduces the damage by half.\n</p><p>An undead creature caught within the globe takes 1d6 points of damage per caster level (maximum 25d6), or half damage if a Reflex save is successful. In addition, the burst results in the destruction of any undead creature specifically harmed by bright light if it fail its save.\n</p><p>The ultraviolet light generated by the spell deals damage to fungi, mold, oozes, and slimes just as if they were undead creatures.\n</p><p><i>Sunburst </i>dispels any darkness spells of lower than 9th level within its area.\n</p><p><i>Arcane Material Component: </i>A piece of sunstone and a naked flame.\n</p>\n<hr/>\n\n\n",
    "snip": "Blinds all within 10 ft., deals 6d6 damage.",
    "spellDuration": "Instantaneous",
    "spellEffect": "",
    "spellArea": "80-ft.-radius burst",
    "spellType": {
      "value": "",
      "_deprecated": true
    },
    "showInQuickbar": false,
    "specialPrepared": false,
    "isDomainSpell": false,
    "specialId": null,
    "attack": {
      "parts": []
    },
    "identifiedName": "Sunburst",
    "changes": [],
    "combatChanges": [],
    "resistances": [],
    "contextNotes": [],
    "activateActions": [],
    "deactivateActions": [],
    "container": "None",
    "containerWeightless": false,
    "customReferenceId": "",
    "requirements": [],
    "creationChanges": [],
    "damageReduction": [],
    "perRoundActions": [],
    "spellDurationData": {
      "value": "",
      "units": "inst",
      "dismissable": false
    },
    "index": {
      "subType": null,
      "uniqueId": ""
    }
  },
  "ownership": {
    "default": 0
  },
  "_stats": {
    "systemId": "D35E",
    "systemVersion": "2.1.3",
    "coreVersion": "10.291",
    "createdTime": 1668846676682,
    "modifiedTime": 1678394290845,
    "lastModifiedBy": "cB3ob9BYxSFYX7sd"
  },
  "_key": "!items!GvT7kiKZsmvnNz7i"
}