{
  "_id": "mXWIlfeqoN9c8r6J",
  "name": "Rod of Lordly Might",
  "type": "equipment",
  "img": "systems/D35E/icons/items/magic/staff/Wand_v2_65.png",
  "effects": [],
  "folder": null,
  "sort": 0,
  "flags": {
    "exportSource": {
      "world": "test",
      "system": "D35E",
      "coreVersion": "0.6.5",
      "systemVersion": 0.82
    },
    "core": {
      "sourceId": "Compendium.D35E.magicitems.mXWIlfeqoN9c8r6J"
    }
  },
  "system": {
    "originVersion": 99,
    "originPack": "",
    "originId": "",
    "possibleUpdate": false,
    "description": {
      "value": "\n      <div topic='Lordly Might' level='8'><p><b>Lordly Might:</b> This rod has functions that are spell-like, and it can also be used as a magic weapon of various sorts. It also has several more mundane uses. The <i>rod of lordly might</i> is metal, thicker than other rods, with a flanged ball at one end and six studlike buttons along its length. (Pushing any of the rod's buttons is equivalent to drawing a weapon.) It weighs 10 pounds.</p><p>The following spell-like functions of the rod can each be used once per day.</p><ul>\n <li> <i>Hold person</i> upon touch, if the wielder so commands (Will DC 14 negates). The wielder must choose to use this power and then succeed on a melee touch attack to activate the power. If the attack fails, the effect is lost.</li>\n <li> <i>Fear</i> upon all enemies viewing it, if the wielder so desires (10-foot maximum range, Will DC 16 partial). Invoking this power is a standard action.</li>\n <li> Deal 2d4 hit points of damage to an opponent on a successful touch attack (Will DC 17 half ) and cure the wielder of a like amount of damage. The wielder must choose to use this power before attacking, as with <i>hold person</i>.</li>\n</ul><p>The following weapon functions of the rod have no limit on the number of times they can be employed.</p><ul>\n <li> In its normal form, the rod can be used as a <i>+2 light mace</i>.</li>\n <li> When button 1 is pushed, the rod becomes a <i>+1 flaming longsword</i>. A blade springs from the ball, with the ball itself becoming the sword's hilt. The weapon lengthens to an overall length of 4 feet.</li>\n <li> When button 2 is pushed, the rod becomes a <i>+4 battleaxe</i>. A wide blade springs forth at the ball, and the whole lengthens to 4 feet.</li>\n <li> When button 3 is pushed, the rod becomes a <i>+3 shortspear</i> or <i>+3 longspear</i>. The spear blade springs forth, and the handle can be lengthened up to 12 feet (wielder's choice), for an overall length of from 6 feet to 15 feet. At its 15-foot length, the rod is suitable for use as a lance.</li>\n</ul><p>The following other functions of the rod also have no limit on the number of times they can be employed.</p><ul>\n <li> Climbing pole/ladder. When button 4 is pushed, a spike that can anchor in granite is extruded from the ball, while the other end sprouts three sharp hooks. The rod lengthens to anywhere between 5 and 50 feet in a single round, stopping when button 4 is pushed again. Horizontal bars three inches long fold out from the sides, 1 foot apart, in staggered progression. The rod is firmly held by the spike and hooks and can bear up to 4,000 pounds. The wielder can retract the pole by pushing button 5.</li>\n <li> The ladder function can be used to force open doors. The wielder plants the rod's base 30 feet or less from the portal to be forced and in line with it, then pushes button 4. The force exerted has a Strength modifier of +12.</li>\n <li> When button 6 is pushed, the rod indicates magnetic north and gives the wielder a knowledge of his approximate depth beneath the surface or height above it.</li>\n</ul><p>Strong enchantment, evocation, necromancy, and transmutation; CL 19th; Craft Rod, Craft Magic Arms and Armor, <i>inflict light wounds</i>,  <i>bull's strength</i>,  <i>flame blade</i>,  <i>hold person</i>,  <i>fear</i>; Price 70,000 gp.</p>\n</div>\n    ",
      "chat": "",
      "unidentified": ""
    },
    "epic": "",
    "psionic": "",
    "nameFormula": "",
    "nameFromFormula": false,
    "tags": [],
    "uniqueId": "",
    "linkId": "",
    "linkSourceId": "",
    "linkImported": false,
    "linkSourceName": "",
    "source": "",
    "classSource": "",
    "userNonRemovable": false,
    "customAttributes": {},
    "customAttributesLocked": false,
    "customTag": "",
    "createdBy": "",
    "quantity": 1,
    "weight": 0,
    "constantWeight": true,
    "price": 70000,
    "resalePrice": "",
    "brokenResalePrice": "",
    "fullResalePrice": false,
    "identified": true,
    "identifiedCurse": false,
    "cursed": false,
    "curseActive": false,
    "hp": {
      "max": 10,
      "value": 10
    },
    "hardness": 0,
    "carried": true,
    "unidentified": {
      "price": 0,
      "name": ""
    },
    "identifiedName": "Rod of Lordly Might",
    "container": "None",
    "containerId": "none",
    "containerWeightless": false,
    "equippedWeightless": false,
    "changes": [],
    "changeFlags": {
      "loseDexToAC": false,
      "noStr": false,
      "noDex": false,
      "noInt": false,
      "noCon": false,
      "oneInt": false,
      "oneWis": false,
      "oneCha": false,
      "noEncumbrance": false,
      "mediumArmorFullSpeed": false,
      "heavyArmorFullSpeed": false,
      "multiAttack": false,
      "multiweaponAttack": false,
      "uncannyDodge": false
    },
    "conditionFlags": {
      "dazzled": false,
      "wildshaped": false,
      "polymorphed": false
    },
    "combatChanges": [],
    "combatChangesRange": {
      "maxFormula": "",
      "max": 0
    },
    "combatChangesAdditionalRanges": {
      "hasAdditionalRanges": false,
      "slider1": {
        "maxFormula": "",
        "max": 0,
        "name": ""
      },
      "slider2": {
        "maxFormula": "",
        "max": 0,
        "name": ""
      },
      "slider3": {
        "maxFormula": "",
        "max": 0,
        "name": ""
      }
    },
    "combatChangesUsesCost": "chargesPerUse",
    "combatChangesApplySpecialActionsOnce": true,
    "combatChangeCustomDisplayName": "",
    "combatChangeCustomReferenceName": "",
    "sizeOverride": "",
    "counterName": "",
    "resistances": [],
    "damageReduction": [],
    "requirements": [],
    "creationChanges": [],
    "measureTemplate": {
      "type": "",
      "size": 0,
      "overrideColor": false,
      "customColor": "",
      "overrideTexture": false,
      "customTexture": ""
    },
    "actionType": "",
    "attackBonus": "",
    "critConfirmBonus": "",
    "damage": {
      "parts": [],
      "alternativeParts": []
    },
    "summon": [],
    "attackParts": [],
    "autoscaleAttackParts": "",
    "formula": "",
    "attackCountFormula": "",
    "maxDamageDice": 0,
    "maxDamageDiceFormula": "",
    "ability": {
      "attack": null,
      "damage": null,
      "damageMult": 1,
      "critRange": 20,
      "critMult": 2,
      "twoHandedOnly": false,
      "vsTouchAc": false
    },
    "save": {
      "dc": 0,
      "description": "",
      "ability": "",
      "type": "",
      "dcAutoType": "",
      "dcAutoAbility": "",
      "originVersion": 97
    },
    "baseCl": "0",
    "sr": false,
    "pr": false,
    "metamagicFeats": {
      "maximized": false,
      "empowered": false,
      "enlarged": false,
      "intensified": false,
      "enhanced": false,
      "enhancedHalf": false,
      "widened": false
    },
    "effectNotes": "",
    "attackNotes": "",
    "specialActions": [],
    "favorite": false,
    "rollTableDraw": {
      "formula": "",
      "name": "",
      "pack": "",
      "id": ""
    },
    "contextNotes": [],
    "enhancements": {
      "uses": {
        "value": 0,
        "max": 0,
        "per": null,
        "rechargeFormula": null,
        "autoDeductCharges": true,
        "allowMultipleUses": false,
        "commonPool": false
      },
      "automation": {
        "updateName": false,
        "updatePrice": false
      },
      "clFormula": "",
      "spellcastingAbility": "",
      "items": []
    },
    "light": {
      "color": "",
      "radius": 0,
      "opacity": 0,
      "alpha": 0.5,
      "lightAngle": 360,
      "type": "",
      "animationSpeed": "",
      "animationIntensity": "",
      "dimRadius": "",
      "emitLight": false
    },
    "material": {
      "data": null
    },
    "equipped": true,
    "equipmentType": "misc",
    "equipmentSubtype": "wondrous",
    "armor": {
      "value": 0,
      "dex": null,
      "acp": 0,
      "enh": 0
    },
    "masterwork": false,
    "melded": false,
    "linkedItems": [],
    "armorType": {
      "value": "",
      "_deprecated": true
    },
    "spellFailure": 0,
    "slot": "slotless",
    "activation": {
      "cost": null,
      "type": ""
    },
    "attack": {
      "parts": []
    },
    "index": {
      "subType": null,
      "uniqueId": ""
    }
  },
  "ownership": {
    "default": 0
  },
  "_stats": {
    "systemId": "D35E",
    "systemVersion": "2.1.3",
    "coreVersion": "10.291",
    "createdTime": null,
    "modifiedTime": 1678394298053,
    "lastModifiedBy": "cB3ob9BYxSFYX7sd"
  },
  "_key": "!items!mXWIlfeqoN9c8r6J"
}