{
  "_id": "A2P5qJhjkgZQBWl3",
  "name": "Goblin",
  "type": "race",
  "img": "systems/D35E/icons/races/goblin.png",
  "effects": [],
  "folder": null,
  "sort": 0,
  "flags": {
    "core": {
      "sourceId": "Compendium.D35E.racialfeatures.A2P5qJhjkgZQBWl3"
    }
  },
  "system": {
    "originVersion": 100,
    "originPack": "",
    "originId": "",
    "possibleUpdate": false,
    "description": {
      "value": "A goblin stands 3 to 3-1/2 feet tall and weigh 40 to 45 pounds. Its eyes are usually dull and glazed, varying in color from red to yellow. A goblin’s skin color ranges from yellow through any shade of orange to a deep red; usually all members of a single tribe are about the same color. Goblins wear clothing of dark leather, tending toward drab, soiled-looking colors.\n<ul>\n<li>+2 Dexterity, –2 Strength, –2 Charisma.\n<li>Humanoid (Goblinoid).\n<li>Small size: +1 bonus to Armor Class, +1 bonus on attack rolls, +4 bonus on Hide checks, –4 penalty on grapple checks, lifting and carrying limits 3/4 of those of Medium characters.\n<li>A goblin’s base land speed is 30 feet.\n<li>Darkvision out to 60 feet.\n<li>+4 racial bonus on Move Silently checks and Ride checks.\n<li>Automatic Languages: Common, Goblin. Bonus Languages: Draconic, Elven, Giant, Gnoll, Orc.\n<li>Favored Class: Rogue.\n<li>Level Adjustment: +0.\n</ul>",
      "chat": "",
      "unidentified": ""
    },
    "epic": "",
    "psionic": "",
    "nameFormula": "",
    "nameFromFormula": false,
    "tags": [],
    "uniqueId": "",
    "linkId": "",
    "linkSourceId": "",
    "linkImported": false,
    "linkSourceName": "",
    "source": "",
    "classSource": "",
    "userNonRemovable": false,
    "customAttributes": {},
    "customAttributesLocked": false,
    "customTag": "",
    "createdBy": "",
    "changes": [
      [
        "4",
        "skill",
        "skill.rid",
        "racial"
      ],
      [
        "4",
        "skill",
        "skill.mos",
        "racial"
      ],
      [
        "2",
        "ability",
        "dex",
        "racial"
      ],
      [
        "-2",
        "ability",
        "str",
        "racial"
      ],
      [
        "-2",
        "ability",
        "cha",
        "racial"
      ]
    ],
    "changeFlags": {
      "loseDexToAC": false,
      "noStr": false,
      "noDex": false,
      "noInt": false,
      "noCon": false,
      "oneInt": false,
      "oneWis": false,
      "oneCha": false,
      "noEncumbrance": false,
      "mediumArmorFullSpeed": false,
      "heavyArmorFullSpeed": false,
      "multiAttack": false,
      "multiweaponAttack": false,
      "uncannyDodge": false,
      "hasted": false,
      "firstChangeTargetSelectableOnDescription": false
    },
    "conditionFlags": {
      "dazzled": false,
      "wildshaped": false,
      "polymorphed": false
    },
    "combatChanges": [],
    "combatChangesRange": {
      "maxFormula": "",
      "max": 0
    },
    "combatChangesAdditionalRanges": {
      "hasAdditionalRanges": false,
      "slider1": {
        "maxFormula": "",
        "max": 0,
        "name": ""
      },
      "slider2": {
        "maxFormula": "",
        "max": 0,
        "name": ""
      },
      "slider3": {
        "maxFormula": "",
        "max": 0,
        "name": ""
      }
    },
    "combatChangesUsesCost": "chargesPerUse",
    "combatChangesApplySpecialActionsOnce": true,
    "combatChangeCustomDisplayName": "",
    "combatChangeCustomReferenceName": "",
    "sizeOverride": "sm",
    "counterName": "",
    "resistances": [],
    "damageReduction": [],
    "requirements": [],
    "creationChanges": [],
    "contextNotes": [],
    "links": {
      "children": []
    },
    "creatureType": "humanoid",
    "la": null,
    "subTypes": [],
    "addedAbilities": [],
    "disabledAbilities": [],
    "damage": {
      "parts": [],
      "alternativeParts": []
    },
    "data": {
      "senses": {
        "lowLight": false
      }
    },
    "senses": {
      "blindsight": null,
      "darkvision": 60,
      "tremorsense": null,
      "truesight": null,
      "lowLight": false,
      "lowLightMultiplier": null
    },
    "equippedWeightless": false,
    "carried": false,
    "resalePrice": null,
    "brokenResalePrice": null,
    "fullResalePrice": false,
    "constantWeight": false,
    "attackParts": [],
    "conditionals": [],
    "specialActions": [],
    "activateActions": [],
    "deactivateActions": [],
    "perRoundActions": [],
    "container": "None",
    "containerWeightless": false,
    "identifiedName": "Goblin",
    "index": {
      "subType": null,
      "uniqueId": ""
    }
  },
  "ownership": {
    "default": 0,
    "kowljhpAAAuoOaJG": 3
  },
  "_stats": {
    "systemId": "D35E",
    "systemVersion": "2.1.3",
    "coreVersion": "10.291",
    "createdTime": null,
    "modifiedTime": 1678394274290,
    "lastModifiedBy": "cB3ob9BYxSFYX7sd"
  },
  "_key": "!items!A2P5qJhjkgZQBWl3"
}